[
  { "title": "apple" },
  { "title": "animales" },
  { "title": "cat" },
  { "title": "mango" },
  { "title": "dog" },
  { "title": "car" },
  { "title": "sun" },
  { "title": "sunset" },
  { "title": "plane" },
  { "title": "parrot" },
  { "title": "people" },
  { "title": "fruits" },
  { "title": "fish" },
  { "title": "building" },
  { "title": "house" },
  { "title": "horse" },
  { "title": "rabbit" },
  { "title": "rainbow" },
  { "title": "flowers" },
  { "title": "Coffe" },
  { "title": "laptops" },
  { "title": "light" }
]
